get_eccc_data/__init__.py
get_eccc_data-0.1.0.dist-info/METADATA
get_eccc_data-0.1.0.dist-info/WHEEL
get_eccc_data-0.1.0.dist-info/top_level.txt
get_eccc_data-0.1.0.dist-info/RECORD
