Metadata-Version: 2.1
Name: get-eccc-data
Version: 0.1.0
Summary: To easily retrieve open-source data provided from ECCC.
Home-page: https://github.com/robertburry/Get_ECCC_Data
Author: Robert Burry
Author-email: robertburrywx@gmail.com
License: MIT
Platform: UNKNOWN
Classifier: License :: OSI Approved :: MIT License
Classifier: Programming Language :: Python
Classifier: Programming Language :: Python :: 3
Classifier: Programming Language :: Python :: 3.6
Classifier: Programming Language :: Python :: Implementation :: CPython
Classifier: Programming Language :: Python :: Implementation :: PyPy
Requires-Python: >=3.6.0
Requires-Dist: pandas (>1)
Requires-Dist: numpy (>1)
